{"software":{"name":"owncloud","major":null,"minor":1,"release_level":"Release candidate","patch":null,"license_name":"gnu_general_public_license_v3","license_label":"GNU GENERAL PUBLIC LICENSE V3","license_sourceurl":"http://www.gnu.org/copyleft/gpl.html","full_title":"Own Cloud","short_title":"owncloud","description":"","icon_url":"https://owncloud.org/wp-content/themes/owncloudorgnew/assets/img/common/favicon.png","language":"php","framework":"apache_php","deployment_type":"web","publisher":"engines","blocking_worker_name":null,"required_memory":192,"recommended_memory":256,"http_protocol":"http_and_https","framework_port_overide":null,"custom_start_script":"","custom_install_script":"","custom_post_install_script":"","service_configurations":[{"publisher_namespace":"EnginesSystem","type_path":"database/sql/mysql","variables":{"name":"_Builder(engine_name)","database_host":"_Builder(mysql_host)","database_name":"_Builder(engine_name)","db_username":"_Builder(engine_name)","db_password":"_Builder(random(10))","db_flavor":"mysql2","collation":"utf8"}},{"publisher_namespace":"EnginesSystem","type_path":"filesystem/local/filesystem","variables":{"name":"_Builder(engine_name)","volume_src":" ","permissions":"rw","engine_path":"data_config"}},{"publisher_namespace":"EnginesSystem","type_path":"cron","variables":{"name":"_Builder(engine_name)","cron_job":"*/15 * * * * php -f /home/app/cron.php \u003e\u003e /home/fs/data_config/cron_oc.log","title":"sync"}}],"persistent_directories":[{"path":"app/data"},{"path":"app/config"}],"replacement_strings":[],"persistent_files":[],"installed_packages":[{"name":"owncloud-8.0.0.tar.bz2","source_url":"https://download.owncloud.org/community/owncloud-8.0.0.tar.bz2","destination":"./","extraction_command":"tar -xpf ","path_to_extracted":"owncloud"}],"system_packages":[{"package":null},{"package":"php5-curl"},{"package":"php5-json"},{"package":"php5-intl"},{"package":"php5-mcrypt"},{"package":"php5-imagick"},{"package":"php5-gd"},{"package":"php-net-ftp"},{"package":"php5-xcache"},{"package":"libav-tools"},{"package":"libreoffice"},{"package":"php5-bz2"},{"package":"php5-openssl"},{"package":"php5-exif"}],"workers":[],"rake_tasks":[],"template_files":[{"title":"config","path":"app/config/config.php","content":"\u003c?php\r\n\r\n$CONFIG = array(\r\n\r\n\r\n'instanceid' =\u003e '',\r\n'passwordsalt' =\u003e '',\r\n\r\n'trusted_domains' =\u003e\r\n  array (\r\n    '_Engines(fqdn)',\r\n   \r\n  ),\r\n\r\n'datadirectory' =\u003e '/home/app/data',\r\n'version' =\u003e '',\r\n'dbtype' =\u003e 'mysql',\r\n'dbhost' =\u003e '_Engines(dbhost)',\r\n'dbuser' =\u003e '_Engines(dbuser)',\r\n'dbname' =\u003e '_Engines(dbname)',\r\n'dbpassword' =\u003e '_Engines(dbpasswd)',\r\n'dbtableprefix' =\u003e '',\r\n'installed' =\u003e false,\r\n'default_language' =\u003e 'en',\r\n'defaultapp' =\u003e 'files',\r\n'knowledgebaseenabled' =\u003e true,\r\n'enable_avatars' =\u003e true,\r\n'allow_user_to_change_display_name' =\u003e true,\r\n'remember_login_cookie_lifetime' =\u003e 60*60*24*15,\r\n'session_lifetime' =\u003e 60 * 60 * 24,\r\n'session_keepalive' =\u003e true,\r\n'skeletondirectory' =\u003e '',\r\n'mail_domain' =\u003e '_Builder(fqdn)',\r\n'mail_from_address' =\u003e 'owncloud',\r\n'mail_smtpdebug' =\u003e false,\r\n'mail_smtpmode' =\u003e 'smtp',\r\n'mail_smtphost' =\u003e '_System(smtp_host)',\r\n'mail_smtpport' =\u003e 25,\r\n'mail_smtptimeout' =\u003e 10,\r\n'mail_smtpsecure' =\u003e '',\r\n'mail_smtpauth' =\u003e false,\r\n'mail_smtpauthtype' =\u003e 'LOGIN',\r\n'mail_smtpname' =\u003e '',\r\n'mail_smtppassword' =\u003e '',\r\n'overwritehost' =\u003e '',\r\n\r\n'overwriteprotocol' =\u003e '',\r\n\r\n'overwritewebroot' =\u003e '',\r\n'overwritecondaddr' =\u003e '',\r\n'overwrite.cli.url' =\u003e '',\r\n'proxy' =\u003e '',\r\n'proxyuserpwd' =\u003e '',\r\n'trashbin_retention_obligation' =\u003e 30,\r\n\r\n\r\n'trashbin_auto_expire' =\u003e true,\r\n'appcodechecker' =\u003e false,\r\n'updatechecker' =\u003e true,\r\n'has_internet_connection' =\u003e true,\r\n'check_for_working_webdav' =\u003e true,\r\n'check_for_working_htaccess' =\u003e true,\r\n'log_type' =\u003e 'owncloud',\r\n'logfile' =\u003e 'owncloud.log',\r\n'loglevel' =\u003e 2,\r\n'logdateformat' =\u003e 'F d, Y H:i:s',\r\n\r\n/**\r\n * The default timezone for logfiles is UTC. You may change this; see\r\n * http://php.net/manual/en/timezones.php\r\n */\r\n'logtimezone' =\u003e '_Engines(TZ)',\r\n          \r\n/**\r\n * Append all database queries and parameters to the log file. Use this only for\r\n * debugging, as your logfile will become huge.\r\n */\r\n'log_query' =\u003e false,\r\n\r\n/**\r\n * Log successful cron runs.\r\n */\r\n'cron_log' =\u003e true,\r\n'log_rotate_size' =\u003e false,\r\n'3rdpartyroot' =\u003e '',\r\n'3rdpartyurl' =\u003e '',\r\n\r\n'customclient_desktop' =\u003e\r\n        'http://owncloud.org/sync-clients/',\r\n'customclient_android' =\u003e\r\n        'https://play.google.com/store/apps/details?id=com.owncloud.android',\r\n'customclient_ios' =\u003e\r\n        'https://itunes.apple.com/us/app/owncloud/id543672169?mt=8',\r\n'appstoreenabled' =\u003e true,\r\n'appstoreurl' =\u003e 'https://api.owncloud.com/v1',\r\n'apps_paths' =\u003e array(\r\n        array(\r\n                'path'=\u003e '/home/app/apps',\r\n                'url' =\u003e '/apps',\r\n                'writable' =\u003e true,\r\n        ),\r\n),\r\n\r\n'enable_previews' =\u003e true,\r\n'preview_max_x' =\u003e null,\r\n'preview_max_y' =\u003e null,\r\n'preview_max_scale_factor' =\u003e 10,\r\n'preview_libreoffice_path' =\u003e  '/usr/lib/libreoffice/program/soffice',\r\n/**\r\n * Use this if LibreOffice/OpenOffice requires additional arguments.\r\n */\r\n'preview_office_cl_parameters' =\u003e\r\n        ' --headless --nologo --nofirststartwizard --invisible --norestore '.\r\n        '-convert-to pdf -outdir ',\r\n'enabledPreviewProviders' =\u003e array(\r\n        'OC\\Preview\\Image',\r\n        'OC\\Preview\\MP3',\r\n        'OC\\Preview\\TXT',\r\n        'OC\\Preview\\MarkDown'\r\n),\r\n'maintenance' =\u003e false,\r\n'singleuser' =\u003e false,\r\n'forcessl' =\u003e false,\r\n'blacklisted_files' =\u003e array('.htaccess'),\r\n'share_folder' =\u003e '/',\r\n'theme' =\u003e '',\r\n'xframe_restriction' =\u003e true,\r\n'cipher' =\u003e 'AES-256-CFB',\r\n\r\n'cache_path' =\u003e '',\r\n'quota_include_external_storage' =\u003e false,\r\n'filesystem_check_changes' =\u003e 1,\r\n'asset-pipeline.enabled' =\u003e false,\r\n'mount_file' =\u003e 'data/mount.json',\r\n'filesystem_cache_readonly' =\u003e false,\r\n\r\n'custom_csp_policy' =\u003e\r\n        \"default-src 'self'; script-src 'self' 'unsafe-eval'; \".\r\n        \"style-src 'self' 'unsafe-inline'; frame-src *; img-src *; \".\r\n        \"font-src 'self' data:; media-src *\",\r\n'secret' =\u003e '_Builder(random(32))',\r\n\r\n);\r\n\r\n  \t"}],"file_write_permissions":[{"path":"owncloud.log","recursive":false},{"path":"apps","recursive":true},{"path":"config","recursive":false},{"path":"lib/private/log","recursive":false}],"custom_php_inis":[{"content":"; Maximum allowed size for uploaded files.\r\nupload_max_filesize = 40M\r\n\r\n; Must be greater than or equal to upload_max_filesize\r\npost_max_size = 40M"}],"apache_htaccess_files":[{"directory":"/home/app/data/","htaccess_content":" /home/app/data/ \t\u003cDirectory /home/app/data/\u003e # Important for security, prevents someone from # uploading a malicious .htaccess AllowOverride None SetHandler none SetHandler default-handler Options -ExecCGI php_flag engine off RemoveHandler .cgi .php .php3 .php4 .php5 .phtml .pl .py .pyc .pyo \u003cFiles *\u003e AllowOverride None SetHandler none SetHandler default-handler Options -ExecCGI php_flag engine off RemoveHandler .cgi .php .php3 .php4 .php5 .phtml .pl .py .pyc .pyo \u003c/Files\u003e \u003c/Directory\u003e "}],"apache_httpd_configurations":[],"apache_modules":[{"os_package":"","module":"rewrite"},{"os_package":"","module":"negotiation"}],"pear_modules":[],"variables":[],"component_sources":[],"component_path":"/home/app/apps","extract_components":true}}